daggery-0.2.6.dist-info/METADATA
daggery-0.2.6.dist-info/WHEEL
daggery-0.2.6.dist-info/entry_points.txt
daggery/__init__.py
daggery/async_dag.py
daggery/async_node.py
daggery/dag.py
daggery/description.py
daggery/node.py
daggery/prevalidate.py
daggery/utils/__init__.py
daggery/utils/decorators.py
daggery/utils/logging.py
examples/__init__.py
examples/fastapi_service.py
examples/request_from_service.py
examples/substitution.py
daggery-0.2.6.dist-info/RECORD
