Metadata-Version: 2.1
Name: daggery
Version: 0.2.6
Author-Email: Daniel Soutar <danielsoutar144@gmail.com>
Requires-Python: <4.0,>=3.10
Requires-Dist: pydantic<3.0.0,>=2.10.2
Requires-Dist: colorlog<7.0.0,>=6.9.0
